imageresize/__init__.py
imageresize/imageresize.py
python_image_resize-0.0.3.dist-info/DESCRIPTION.rst
python_image_resize-0.0.3.dist-info/METADATA
python_image_resize-0.0.3.dist-info/metadata.json
python_image_resize-0.0.3.dist-info/RECORD
python_image_resize-0.0.3.dist-info/top_level.txt
python_image_resize-0.0.3.dist-info/WHEEL
