Metadata-Version: 2.0
Name: python-image-resize
Version: 0.0.3
Summary: A Small python package to easily resize images
Home-page: https://github.com/charlesthk/image-tools
Author: Charles TISSIER
Author-email: charles@vingtcinq.io
License: MIT
Keywords: image resizing python
Platform: UNKNOWN
Classifier: Development Status :: 5 - Production/Stable
Classifier: Intended Audience :: Developers
Classifier: Topic :: Software Development :: Libraries :: Python Modules
Classifier: License :: OSI Approved :: MIT License
Classifier: Programming Language :: Python :: 2.7
Requires-Dist: pillow
